pitop/simulation/__init__.py
pitop/simulation/color.py
pitop/simulation/events.py
pitop/simulation/port_label.py
pitop/simulation/simsprite.py
pitop/simulation/simulation.py
pitop/simulation/sprites.py
pitop/simulation/utils.py
pitop/simulation/images/Button.png
pitop/simulation/images/Button_pressed.png
pitop/simulation/images/Buzzer.png
pitop/simulation/images/LED_green_off.png
pitop/simulation/images/LED_green_on.png
pitop/simulation/images/LED_red_off.png
pitop/simulation/images/LED_red_on.png
pitop/simulation/images/LED_yellow_off.png
pitop/simulation/images/LED_yellow_on.png
pitop/simulation/images/LightSensor.png
pitop/simulation/images/Pitop.png
pitop/simulation/images/Potentiometer.png
pitop/simulation/images/Readme.md
pitop/simulation/images/SoundSensor.png
pitop/simulation/images/UltrasonicSensor.png
pitop/simulation/images/__init__.py
pitop/simulation/images/angle_icon.png
pitop/simulation/images/buzzer_sound_icon.png
pitop/simulation/images/distance_icon.png
pitop/simulation/images/lightbulb_icon.png
pitop/simulation/images/speaker_icon.png
pitop/simulation/virtual_hardware/__init__.py
pitop/simulation/virtual_hardware/fonts.py
pitop/simulation/virtual_hardware/pitop.py
pitop/simulation/virtual_hardware/vendor/__init__.py
pitop/simulation/virtual_hardware/vendor/Mock/GPIO.py
pitop/simulation/virtual_hardware/vendor/Mock/__init__.py
pitop/simulation/widgets/README.md
pitop/simulation/widgets/slider.py
pitop/simulation/widgets/widget.py
pitop.simulation-0.34.3.post1.dist-info/METADATA
pitop.simulation-0.34.3.post1.dist-info/WHEEL
pitop.simulation-0.34.3.post1.dist-info/top_level.txt
pitop.simulation-0.34.3.post1.dist-info/RECORD
